CHANGES.rst
MANIFEST.in
README.rst
setup.py
mr/__init__.py
mr.inquisition.egg-info/PKG-INFO
mr.inquisition.egg-info/SOURCES.txt
mr.inquisition.egg-info/dependency_links.txt
mr.inquisition.egg-info/entry_points.txt
mr.inquisition.egg-info/namespace_packages.txt
mr.inquisition.egg-info/not-zip-safe
mr.inquisition.egg-info/requires.txt
mr.inquisition.egg-info/top_level.txt
mr/inquisition/__init__.py
mr/inquisition/browser.py
mr/inquisition/configure.zcml
mr/inquisition/templates/count_types.pt
mr/inquisition/templates/list_objects.pt
mr/inquisition/templates/main.pt
mr/inquisition/templates/matrix.pt