Metadata-Version: 1.1
Name: mr.inquisition
Version: 0.2
Summary: A package to help with exploring a Plone site.
Home-page: https://github.com/collective/mr.inquisition
Author: Mark van Lent
Author-email: mark@vlent.nl
License: GPL
Keywords: information objects plone
Platform: UNKNOWN
Classifier: Intended Audience :: Developers
Classifier: Framework :: Plone
Classifier: Framework :: Plone :: 3.3
Classifier: Framework :: Plone :: 4.0
Classifier: Framework :: Plone :: 4.1
Classifier: Framework :: Plone :: 4.2
Classifier: Framework :: Plone :: 4.3
Classifier: Programming Language :: Python
Classifier: Programming Language :: Python :: 2.4
Classifier: Programming Language :: Python :: 2.6
Classifier: Programming Language :: Python :: 2.7
Classifier: Topic :: Software Development :: Libraries :: Python Modules
